dislog/__init__.py
dislog/handler.py
dislog/py.typed
dislog-3.0.0.dist-info/LICENSE
dislog-3.0.0.dist-info/METADATA
dislog-3.0.0.dist-info/WHEEL
dislog-3.0.0.dist-info/top_level.txt
dislog-3.0.0.dist-info/RECORD
