Metadata-Version: 2.1
Name: dislog
Version: 3.0.0
Summary: Provides an interface for using a discord webhook as a logger.
Home-page: https://github.com/regulad/dislog
Download-URL: https://github.com/regulad/dislog/archive/refs/heads/master.zip
Author: regulad
Author-email: regulad@regulad.xyz
License: GPLv3
Keywords: requests
Classifier: Intended Audience :: Developers
Classifier: Natural Language :: English
Classifier: Operating System :: OS Independent
Classifier: License :: OSI Approved :: GNU General Public License v3 (GPLv3)
Classifier: Development Status :: 5 - Production/Stable
Classifier: Typing :: Typed
Classifier: Topic :: System :: Logging
Classifier: Programming Language :: Python :: Implementation :: CPython
Classifier: Programming Language :: Python :: 3
Classifier: Programming Language :: Python :: 3.8
Classifier: Programming Language :: Python :: 3.9
Classifier: Programming Language :: Python :: 3.10
Classifier: Programming Language :: Python :: 3.11
Requires-Python: <4,>=3.8
License-File: LICENSE
Requires-Dist: aiohttp (<4,>=3.8.4)
Provides-Extra: discordpy
Requires-Dist: discord.py (<3,>=1.4) ; extra == 'discordpy'
Provides-Extra: speed
Requires-Dist: discord.py[speed] ; extra == 'speed'
Provides-Extra: sync
Requires-Dist: requests (<3,>=2.27.1) ; extra == 'sync'
Provides-Extra: test
Requires-Dist: pytest (<8,>=7.2.1) ; extra == 'test'
Requires-Dist: pytest-asyncio (<1,>=0.20.3) ; extra == 'test'
Provides-Extra: type
Requires-Dist: mypy (<2,>=1.0.1) ; extra == 'type'
Requires-Dist: types-requests (<3,>=2.28.11.13) ; extra == 'type'
